xlrd/__init__.py
xlrd/biffh.py
xlrd/book.py
xlrd/compdoc.py
xlrd/formatting.py
xlrd/formula.py
xlrd/info.py
xlrd/sheet.py
xlrd/timemachine.py
xlrd/xldate.py
xlrd_2024-2.0.1.data/scripts/runxlrd.py
xlrd_2024-2.0.1.dist-info/LICENSE
xlrd_2024-2.0.1.dist-info/METADATA
xlrd_2024-2.0.1.dist-info/WHEEL
xlrd_2024-2.0.1.dist-info/top_level.txt
xlrd_2024-2.0.1.dist-info/RECORD
